[
    {"test_name": "Last Configuration Started", "market_code": "AT/de", "model_code": "C174"},
    {"test_name": "Last Configuration Started", "market_code": "BE/nl", "model_code": "C174"},
    {"test_name": "Last Configuration Started", "market_code": "BE/fr", "model_code": "C174"},
    {"test_name": "Last Configuration Started", "market_code": "CH/de", "model_code": "C174"},
    {"test_name": "Last Configuration Started", "market_code": "CH/fr", "model_code": "C174"},
    {"test_name": "Last Configuration Started", "market_code": "CH/it", "model_code": "C174"},
    {"test_name": "Last Configuration Started", "market_code": "GB/en", "model_code": "C174"},
    {"test_name": "Last Configuration Started", "market_code": "CZ/cs", "model_code": "C174"},
    {"test_name": "Last Configuration Started", "market_code": "DE/de", "model_code": "C174"},
    {"test_name": "Last Configuration Started", "market_code": "DK/da", "model_code": "C174"},
    {"test_name": "Last Configuration Started", "market_code": "ES/es", "model_code": "C174"},
    {"test_name": "Last Configuration Started", "market_code": "FR/fr", "model_code": "C174"},
    {"test_name": "Last Configuration Started", "market_code": "HU/hu", "model_code": "C174"},
    {"test_name": "Last Configuration Started", "market_code": "IT/it", "model_code": "C174"},
    {"test_name": "Last Configuration Started", "market_code": "LU/de", "model_code": "C174"},
    {"test_name": "Last Configuration Started", "market_code": "LU/fr", "model_code": "C174"},
    {"test_name": "Last Configuration Started", "market_code": "NL/nl", "model_code": "C174"},
    {"test_name": "Last Configuration Started", "market_code": "PL/pl", "model_code": "C174"},
    {"test_name": "Last Configuration Started", "market_code": "PT/pt", "model_code": "C174"},
    {"test_name": "Last Configuration Started", "market_code": "RO/ro", "model_code": "C174"},
    {"test_name": "Last Configuration Started", "market_code": "SE/sv", "model_code": "C174"},
    {"test_name": "Last Configuration Started", "market_code": "SK/sk", "model_code": "C174"}
]